{
    "annotations": {
      "list": [
        {
          "builtIn": 1,
          "datasource": "-- Grafana --",
          "enable": true,
          "hide": true,
          "iconColor": "rgba(0, 211, 255, 1)",
          "name": "Annotations & Alerts",
          "target": {
            "limit": 100,
            "matchAny": false,
            "tags": [],
            "type": "dashboard"
          },
          "type": "dashboard"
        }
      ]
    },
    "editable": true,
    "fiscalYearStartMonth": 0,
    "graphTooltip": 0,
    "id": 28,
    "iteration": 1701276863848,
    "links": [],
    "liveNow": false,
    "panels": [
      {
        "collapsed": true,
        "gridPos": {
          "h": 1,
          "w": 24,
          "x": 0,
          "y": 0
        },
        "id": 16,
        "panels": [
          {
            "datasource": {
              "type": "prometheus",
              "uid": "${datasource}"
            },
            "fieldConfig": {
              "defaults": {
                "color": {
                  "mode": "thresholds"
                },
                "mappings": [],
                "max": 100,
                "min": 0,
                "thresholds": {
                  "mode": "absolute",
                  "steps": [
                    {
                      "color": "green",
                      "value": null
                    }
                  ]
                },
                "unit": "percent"
              },
              "overrides": []
            },
            "gridPos": {
              "h": 8,
              "w": 8,
              "x": 0,
              "y": 1
            },
            "id": 14,
            "options": {
              "orientation": "auto",
              "reduceOptions": {
                "calcs": [
                  "lastNotNull"
                ],
                "fields": "",
                "values": false
              },
              "showThresholdLabels": false,
              "showThresholdMarkers": true,
              "text": {}
            },
            "pluginVersion": "8.3.3",
            "targets": [
              {
                "datasource": {
                  "type": "prometheus",
                  "uid": "${datasource}"
                },
                "exemplar": true,
                "expr": "(1 - avg by (node) (irate(node_cpu_seconds_total{mode=\"idle\", instance=\"$node\"}[5m]))) * 100",
                "interval": "",
                "legendFormat": "",
                "refId": "A"
              }
            ],
            "title": "cpu usage by %",
            "type": "gauge"
          },
          {
            "datasource": {
              "type": "prometheus",
              "uid": "${datasource}"
            },
            "fieldConfig": {
              "defaults": {
                "color": {
                  "mode": "thresholds"
                },
                "mappings": [],
                "max": 30,
                "min": 0,
                "thresholds": {
                  "mode": "absolute",
                  "steps": [
                    {
                      "color": "green",
                      "value": null
                    },
                    {
                      "color": "red",
                      "value": 80
                    }
                  ]
                },
                "unit": "string"
              },
              "overrides": []
            },
            "gridPos": {
              "h": 8,
              "w": 7,
              "x": 8,
              "y": 1
            },
            "id": 12,
            "options": {
              "orientation": "auto",
              "reduceOptions": {
                "calcs": [
                  "lastNotNull"
                ],
                "fields": "",
                "values": false
              },
              "showThresholdLabels": false,
              "showThresholdMarkers": true,
              "text": {}
            },
            "pluginVersion": "8.3.3",
            "targets": [
              {
                "datasource": {
                  "type": "prometheus",
                  "uid": "${datasource}"
                },
                "exemplar": true,
                "expr": "count(kube_pod_info{job=\"kube-state-metrics\", node=~\"$node\"}) by (node)\n",
                "interval": "",
                "legendFormat": "",
                "refId": "A"
              }
            ],
            "title": "pods runnig on node",
            "type": "gauge"
          },
          {
            "datasource": {
              "type": "prometheus",
              "uid": "${datasource}"
            },
            "fieldConfig": {
              "defaults": {
                "color": {
                  "mode": "thresholds"
                },
                "mappings": [],
                "max": 100,
                "min": 0,
                "thresholds": {
                  "mode": "percentage",
                  "steps": [
                    {
                      "color": "green",
                      "value": null
                    }
                  ]
                },
                "unit": "percent"
              },
              "overrides": []
            },
            "gridPos": {
              "h": 8,
              "w": 9,
              "x": 15,
              "y": 1
            },
            "id": 10,
            "options": {
              "orientation": "auto",
              "reduceOptions": {
                "calcs": [
                  "lastNotNull"
                ],
                "fields": "",
                "values": false
              },
              "showThresholdLabels": false,
              "showThresholdMarkers": true
            },
            "pluginVersion": "8.3.3",
            "targets": [
              {
                "datasource": {
                  "type": "prometheus",
                  "uid": "${datasource}"
                },
                "exemplar": true,
                "expr": "sum(kube_pod_status_phase{phase=\"Running\"}) / sum(kube_pod_status_phase)*100",
                "interval": "",
                "legendFormat": "",
                "refId": "A"
              }
            ],
            "title": "Pod runnig ratio",
            "type": "gauge"
          }
        ],
        "title": "node ",
        "type": "row"
      },
      {
        "collapsed": true,
        "gridPos": {
          "h": 1,
          "w": 24,
          "x": 0,
          "y": 1
        },
        "id": 34,
        "panels": [
          {
            "datasource": {
              "type": "prometheus",
              "uid": "${datasource}"
            },
            "fieldConfig": {
              "defaults": {
                "color": {
                  "mode": "thresholds"
                },
                "mappings": [],
                "max": 100,
                "min": 0,
                "thresholds": {
                  "mode": "absolute",
                  "steps": [
                    {
                      "color": "green",
                      "value": null
                    }
                  ]
                }
              },
              "overrides": []
            },
            "gridPos": {
              "h": 8,
              "w": 7,
              "x": 0,
              "y": 2
            },
            "id": 46,
            "options": {
              "orientation": "auto",
              "reduceOptions": {
                "calcs": [
                  "lastNotNull"
                ],
                "fields": "",
                "values": false
              },
              "showThresholdLabels": false,
              "showThresholdMarkers": true
            },
            "pluginVersion": "8.3.3",
            "targets": [
              {
                "datasource": {
                  "type": "prometheus",
                  "uid": "${datasource}"
                },
                "exemplar": true,
                "expr": "sum(kube_pod_container_status_restarts_total{namespace=~\"$namespace\"}) by (namespace)\n",
                "interval": "",
                "legendFormat": "",
                "refId": "A"
              }
            ],
            "title": "pod restats in name space ",
            "type": "gauge"
          },
          {
            "datasource": {
              "type": "prometheus",
              "uid": "${datasource}"
            },
            "fieldConfig": {
              "defaults": {
                "color": {
                  "mode": "thresholds"
                },
                "mappings": [],
                "max": 8,
                "min": 0,
                "thresholds": {
                  "mode": "absolute",
                  "steps": [
                    {
                      "color": "green",
                      "value": null
                    },
                    {
                      "color": "red",
                      "value": 80
                    }
                  ]
                },
                "unit": "none"
              },
              "overrides": []
            },
            "gridPos": {
              "h": 8,
              "w": 5,
              "x": 7,
              "y": 2
            },
            "id": 36,
            "options": {
              "orientation": "auto",
              "reduceOptions": {
                "calcs": [
                  "lastNotNull"
                ],
                "fields": "",
                "values": false
              },
              "showThresholdLabels": false,
              "showThresholdMarkers": true
            },
            "pluginVersion": "8.3.3",
            "targets": [
              {
                "datasource": {
                  "type": "prometheus",
                  "uid": "${datasource}"
                },
                "exemplar": true,
                "expr": "(\n  sum(rate(container_cpu_usage_seconds_total{namespace=~\"$namespace\"}[5m])) by (namespace)\n  / \n  8\n) * 100\n",
                "interval": "",
                "legendFormat": "",
                "refId": "A"
              }
            ],
            "title": "cpu usage by name sapce",
            "type": "gauge"
          },
          {
            "datasource": {
              "type": "prometheus",
              "uid": "${datasource}"
            },
            "fieldConfig": {
              "defaults": {
                "color": {
                  "mode": "thresholds"
                },
                "mappings": [],
                "max": 30,
                "min": 0,
                "thresholds": {
                  "mode": "absolute",
                  "steps": [
                    {
                      "color": "green",
                      "value": null
                    },
                    {
                      "color": "red",
                      "value": 80
                    }
                  ]
                }
              },
              "overrides": []
            },
            "gridPos": {
              "h": 8,
              "w": 5,
              "x": 12,
              "y": 2
            },
            "id": 44,
            "options": {
              "orientation": "auto",
              "reduceOptions": {
                "calcs": [
                  "lastNotNull"
                ],
                "fields": "",
                "values": false
              },
              "showThresholdLabels": false,
              "showThresholdMarkers": true
            },
            "pluginVersion": "8.3.3",
            "targets": [
              {
                "datasource": {
                  "type": "prometheus",
                  "uid": "${datasource}"
                },
                "exemplar": true,
                "expr": "count(kube_pod_info{namespace=~\"$namespace\"}) by (namespace)",
                "interval": "",
                "legendFormat": "",
                "refId": "A"
              }
            ],
            "title": "pod per name sapce",
            "type": "gauge"
          },
          {
            "datasource": {
              "type": "prometheus",
              "uid": "${datasource}"
            },
            "fieldConfig": {
              "defaults": {
                "color": {
                  "mode": "thresholds"
                },
                "mappings": [],
                "max": 100,
                "min": 0,
                "thresholds": {
                  "mode": "absolute",
                  "steps": [
                    {
                      "color": "green",
                      "value": null
                    }
                  ]
                }
              },
              "overrides": []
            },
            "gridPos": {
              "h": 8,
              "w": 7,
              "x": 17,
              "y": 2
            },
            "id": 48,
            "options": {
              "orientation": "auto",
              "reduceOptions": {
                "calcs": [
                  "lastNotNull"
                ],
                "fields": "",
                "values": false
              },
              "showThresholdLabels": false,
              "showThresholdMarkers": true
            },
            "pluginVersion": "8.3.3",
            "targets": [
              {
                "datasource": {
                  "type": "prometheus",
                  "uid": "${datasource}"
                },
                "exemplar": true,
                "expr": "count(kube_deployment_created{namespace=~\"$namespace\"}) by (namespace)\n",
                "interval": "",
                "legendFormat": "",
                "refId": "A"
              }
            ],
            "title": "Deployment per name sapce ",
            "type": "gauge"
          },
          {
            "datasource": {
              "type": "prometheus",
              "uid": "${datasource}"
            },
            "fieldConfig": {
              "defaults": {
                "color": {
                  "mode": "palette-classic"
                },
                "custom": {
                  "axisLabel": "",
                  "axisPlacement": "auto",
                  "barAlignment": 0,
                  "drawStyle": "line",
                  "fillOpacity": 0,
                  "gradientMode": "none",
                  "hideFrom": {
                    "legend": false,
                    "tooltip": false,
                    "viz": false
                  },
                  "lineInterpolation": "linear",
                  "lineWidth": 3,
                  "pointSize": 5,
                  "scaleDistribution": {
                    "type": "linear"
                  },
                  "showPoints": "never",
                  "spanNulls": false,
                  "stacking": {
                    "group": "A",
                    "mode": "none"
                  },
                  "thresholdsStyle": {
                    "mode": "off"
                  }
                },
                "mappings": [],
                "thresholds": {
                  "mode": "absolute",
                  "steps": [
                    {
                      "color": "green",
                      "value": null
                    },
                    {
                      "color": "red",
                      "value": 80
                    }
                  ]
                },
                "unit": "binBps"
              },
              "overrides": [
                {
                  "__systemRef": "hideSeriesFrom",
                  "matcher": {
                    "id": "byNames",
                    "options": {
                      "mode": "exclude",
                      "names": [
                        "{namespace=\"monitoring\"}"
                      ],
                      "prefix": "All except:",
                      "readOnly": true
                    }
                  },
                  "properties": [
                    {
                      "id": "custom.hideFrom",
                      "value": {
                        "legend": false,
                        "tooltip": false,
                        "viz": false
                      }
                    }
                  ]
                }
              ]
            },
            "gridPos": {
              "h": 8,
              "w": 12,
              "x": 0,
              "y": 10
            },
            "id": 40,
            "options": {
              "legend": {
                "calcs": [],
                "displayMode": "list",
                "placement": "bottom"
              },
              "tooltip": {
                "mode": "single"
              }
            },
            "targets": [
              {
                "datasource": {
                  "type": "prometheus",
                  "uid": "${datasource}"
                },
                "exemplar": true,
                "expr": "sum(rate(container_network_receive_bytes_total{namespace=~\"$namespace\"}[5m])) by (namespace)",
                "interval": "",
                "legendFormat": "receive",
                "refId": "A"
              },
              {
                "datasource": {
                  "type": "prometheus",
                  "uid": "${datasource}"
                },
                "exemplar": true,
                "expr": "sum(rate(container_network_transmit_bytes_total{namespace=~\"$namespace\"}[5m])) by (namespace)\n",
                "hide": false,
                "interval": "",
                "legendFormat": "transmit",
                "refId": "B"
              }
            ],
            "title": "Network I/O receive/transmit by Namespace ",
            "type": "timeseries"
          },
          {
            "datasource": {
              "type": "prometheus",
              "uid": "${datasource}"
            },
            "fieldConfig": {
              "defaults": {
                "color": {
                  "mode": "palette-classic"
                },
                "custom": {
                  "axisLabel": "",
                  "axisPlacement": "auto",
                  "barAlignment": 0,
                  "drawStyle": "line",
                  "fillOpacity": 0,
                  "gradientMode": "none",
                  "hideFrom": {
                    "legend": false,
                    "tooltip": false,
                    "viz": false
                  },
                  "lineInterpolation": "smooth",
                  "lineWidth": 3,
                  "pointSize": 5,
                  "scaleDistribution": {
                    "type": "linear"
                  },
                  "showPoints": "never",
                  "spanNulls": false,
                  "stacking": {
                    "group": "A",
                    "mode": "none"
                  },
                  "thresholdsStyle": {
                    "mode": "off"
                  }
                },
                "mappings": [],
                "thresholds": {
                  "mode": "absolute",
                  "steps": [
                    {
                      "color": "green",
                      "value": null
                    },
                    {
                      "color": "red",
                      "value": 80
                    }
                  ]
                },
                "unit": "bytes"
              },
              "overrides": [
                {
                  "__systemRef": "hideSeriesFrom",
                  "matcher": {
                    "id": "byNames",
                    "options": {
                      "mode": "exclude",
                      "names": [
                        "{namespace=\"monitoring\"}"
                      ],
                      "prefix": "All except:",
                      "readOnly": true
                    }
                  },
                  "properties": [
                    {
                      "id": "custom.hideFrom",
                      "value": {
                        "legend": false,
                        "tooltip": false,
                        "viz": false
                      }
                    }
                  ]
                }
              ]
            },
            "gridPos": {
              "h": 8,
              "w": 12,
              "x": 12,
              "y": 10
            },
            "id": 42,
            "options": {
              "legend": {
                "calcs": [],
                "displayMode": "list",
                "placement": "bottom"
              },
              "tooltip": {
                "mode": "single"
              }
            },
            "targets": [
              {
                "datasource": {
                  "type": "prometheus",
                  "uid": "${datasource}"
                },
                "exemplar": true,
                "expr": "sum(rate(container_fs_reads_bytes_total{namespace=~\"$namespace\"}[5m])) by (namespace)\n",
                "interval": "",
                "legendFormat": "read",
                "refId": "A"
              },
              {
                "datasource": {
                  "type": "prometheus",
                  "uid": "${datasource}"
                },
                "exemplar": true,
                "expr": "sum(rate(container_fs_writes_bytes_total{namespace=~\"$namespace\"}[5m])) by (namespace)",
                "hide": false,
                "interval": "",
                "legendFormat": "writes",
                "refId": "B"
              }
            ],
            "title": "Disk I/O Read/Writes by Namespace",
            "type": "timeseries"
          },
          {
            "datasource": {
              "type": "prometheus",
              "uid": "${datasource}"
            },
            "fieldConfig": {
              "defaults": {
                "color": {
                  "mode": "palette-classic"
                },
                "custom": {
                  "axisLabel": "",
                  "axisPlacement": "auto",
                  "barAlignment": 0,
                  "drawStyle": "line",
                  "fillOpacity": 0,
                  "gradientMode": "none",
                  "hideFrom": {
                    "legend": false,
                    "tooltip": false,
                    "viz": false
                  },
                  "lineInterpolation": "linear",
                  "lineWidth": 3,
                  "pointSize": 5,
                  "scaleDistribution": {
                    "type": "linear"
                  },
                  "showPoints": "never",
                  "spanNulls": false,
                  "stacking": {
                    "group": "A",
                    "mode": "none"
                  },
                  "thresholdsStyle": {
                    "mode": "off"
                  }
                },
                "mappings": [],
                "thresholds": {
                  "mode": "absolute",
                  "steps": [
                    {
                      "color": "green",
                      "value": null
                    },
                    {
                      "color": "red",
                      "value": 80
                    }
                  ]
                },
                "unit": "bytes"
              },
              "overrides": []
            },
            "gridPos": {
              "h": 7,
              "w": 24,
              "x": 0,
              "y": 18
            },
            "id": 38,
            "options": {
              "legend": {
                "calcs": [],
                "displayMode": "list",
                "placement": "bottom"
              },
              "tooltip": {
                "mode": "single"
              }
            },
            "targets": [
              {
                "datasource": {
                  "type": "prometheus",
                  "uid": "${datasource}"
                },
                "exemplar": true,
                "expr": "sum(container_memory_usage_bytes{namespace=~\"$namespace\"}) by (namespace)",
                "interval": "",
                "legendFormat": "",
                "refId": "A"
              }
            ],
            "title": "Memory Usage by Namespace",
            "type": "timeseries"
          }
        ],
        "title": "name space",
        "type": "row"
      },
      {
        "collapsed": true,
        "gridPos": {
          "h": 1,
          "w": 24,
          "x": 0,
          "y": 2
        },
        "id": 26,
        "panels": [
          {
            "datasource": {
              "type": "prometheus",
              "uid": "${datasource}"
            },
            "fieldConfig": {
              "defaults": {
                "color": {
                  "mode": "palette-classic"
                },
                "custom": {
                  "axisLabel": "",
                  "axisPlacement": "auto",
                  "barAlignment": 0,
                  "drawStyle": "line",
                  "fillOpacity": 0,
                  "gradientMode": "none",
                  "hideFrom": {
                    "legend": false,
                    "tooltip": false,
                    "viz": false
                  },
                  "lineInterpolation": "smooth",
                  "lineWidth": 3,
                  "pointSize": 5,
                  "scaleDistribution": {
                    "type": "linear"
                  },
                  "showPoints": "never",
                  "spanNulls": false,
                  "stacking": {
                    "group": "A",
                    "mode": "none"
                  },
                  "thresholdsStyle": {
                    "mode": "off"
                  }
                },
                "mappings": [],
                "thresholds": {
                  "mode": "absolute",
                  "steps": [
                    {
                      "color": "green",
                      "value": null
                    },
                    {
                      "color": "red",
                      "value": 80
                    }
                  ]
                },
                "unit": "binBps"
              },
              "overrides": [
                {
                  "__systemRef": "hideSeriesFrom",
                  "matcher": {
                    "id": "byNames",
                    "options": {
                      "mode": "exclude",
                      "names": [
                        "{pod=\"blackbox-exporter-6b79c4588b-t6hmp\"}"
                      ],
                      "prefix": "All except:",
                      "readOnly": true
                    }
                  },
                  "properties": [
                    {
                      "id": "custom.hideFrom",
                      "value": {
                        "legend": false,
                        "tooltip": false,
                        "viz": false
                      }
                    }
                  ]
                }
              ]
            },
            "gridPos": {
              "h": 8,
              "w": 12,
              "x": 0,
              "y": 3
            },
            "id": 28,
            "options": {
              "legend": {
                "calcs": [],
                "displayMode": "list",
                "placement": "bottom"
              },
              "tooltip": {
                "mode": "single"
              }
            },
            "targets": [
              {
                "datasource": {
                  "type": "prometheus",
                  "uid": "${datasource}"
                },
                "exemplar": true,
                "expr": "sum(rate(container_network_receive_bytes_total{node=~\"$node\", namespace=~\"$namespace\", pod=~\"$pod\"}[5m])) by (pod)",
                "interval": "",
                "legendFormat": "receive",
                "refId": "A"
              },
              {
                "datasource": {
                  "type": "prometheus",
                  "uid": "${datasource}"
                },
                "exemplar": true,
                "expr": "sum(rate(container_network_transmit_bytes_total{node=~\"$node\", namespace=~\"$namespace\", pod=~\"$pod\"}[5m])) by (pod)",
                "hide": false,
                "interval": "",
                "legendFormat": "transmit",
                "refId": "B"
              }
            ],
            "title": "Network Traffic Received for pod",
            "type": "timeseries"
          },
          {
            "datasource": {
              "type": "prometheus",
              "uid": "${datasource}"
            },
            "fieldConfig": {
              "defaults": {
                "color": {
                  "mode": "palette-classic"
                },
                "custom": {
                  "axisLabel": "",
                  "axisPlacement": "auto",
                  "barAlignment": 0,
                  "drawStyle": "line",
                  "fillOpacity": 0,
                  "gradientMode": "none",
                  "hideFrom": {
                    "legend": false,
                    "tooltip": false,
                    "viz": false
                  },
                  "lineInterpolation": "smooth",
                  "lineWidth": 3,
                  "pointSize": 5,
                  "scaleDistribution": {
                    "type": "linear"
                  },
                  "showPoints": "never",
                  "spanNulls": false,
                  "stacking": {
                    "group": "A",
                    "mode": "none"
                  },
                  "thresholdsStyle": {
                    "mode": "off"
                  }
                },
                "mappings": [],
                "thresholds": {
                  "mode": "absolute",
                  "steps": [
                    {
                      "color": "green",
                      "value": null
                    },
                    {
                      "color": "red",
                      "value": 80
                    }
                  ]
                }
              },
              "overrides": [
                {
                  "__systemRef": "hideSeriesFrom",
                  "matcher": {
                    "id": "byNames",
                    "options": {
                      "mode": "exclude",
                      "names": [
                        "{pod=\"prometheus-k8s-1\"}"
                      ],
                      "prefix": "All except:",
                      "readOnly": true
                    }
                  },
                  "properties": [
                    {
                      "id": "custom.hideFrom",
                      "value": {
                        "legend": false,
                        "tooltip": false,
                        "viz": false
                      }
                    }
                  ]
                }
              ]
            },
            "gridPos": {
              "h": 8,
              "w": 12,
              "x": 12,
              "y": 3
            },
            "id": 32,
            "options": {
              "legend": {
                "calcs": [],
                "displayMode": "list",
                "placement": "bottom"
              },
              "tooltip": {
                "mode": "single"
              }
            },
            "pluginVersion": "8.3.3",
            "targets": [
              {
                "datasource": {
                  "type": "prometheus",
                  "uid": "${datasource}"
                },
                "exemplar": true,
                "expr": "sum(rate(container_fs_reads_bytes_total{node=~\"$node\", namespace=~\"$namespace\", pod=~\"$pod\"}[5m])) by (pod)",
                "interval": "",
                "legendFormat": "read",
                "refId": "A"
              },
              {
                "datasource": {
                  "type": "prometheus",
                  "uid": "${datasource}"
                },
                "exemplar": true,
                "expr": "sum(rate(container_fs_writes_bytes_total{node=~\"$node\", namespace=~\"$namespace\", pod=~\"$pod\"}[5m])) by (pod)",
                "hide": false,
                "interval": "",
                "legendFormat": "write",
                "refId": "B"
              }
            ],
            "title": "Disk I/O read/write for pod ",
            "type": "timeseries"
          }
        ],
        "title": "pod",
        "type": "row"
      },
      {
        "collapsed": true,
        "gridPos": {
          "h": 1,
          "w": 24,
          "x": 0,
          "y": 3
        },
        "id": 22,
        "panels": [
          {
            "datasource": {
              "type": "prometheus",
              "uid": "${datasource}"
            },
            "fieldConfig": {
              "defaults": {
                "color": {
                  "mode": "palette-classic"
                },
                "custom": {
                  "axisLabel": "",
                  "axisPlacement": "auto",
                  "barAlignment": 0,
                  "drawStyle": "line",
                  "fillOpacity": 100,
                  "gradientMode": "none",
                  "hideFrom": {
                    "legend": false,
                    "tooltip": false,
                    "viz": false
                  },
                  "lineInterpolation": "smooth",
                  "lineStyle": {
                    "fill": "solid"
                  },
                  "lineWidth": 0,
                  "pointSize": 5,
                  "scaleDistribution": {
                    "type": "linear"
                  },
                  "showPoints": "never",
                  "spanNulls": false,
                  "stacking": {
                    "group": "A",
                    "mode": "none"
                  },
                  "thresholdsStyle": {
                    "mode": "off"
                  }
                },
                "mappings": [],
                "thresholds": {
                  "mode": "absolute",
                  "steps": [
                    {
                      "color": "green",
                      "value": null
                    },
                    {
                      "color": "red",
                      "value": 80
                    }
                  ]
                }
              },
              "overrides": []
            },
            "gridPos": {
              "h": 8,
              "w": 12,
              "x": 0,
              "y": 4
            },
            "id": 20,
            "options": {
              "legend": {
                "calcs": [],
                "displayMode": "list",
                "placement": "bottom"
              },
              "tooltip": {
                "mode": "single"
              }
            },
            "targets": [
              {
                "datasource": {
                  "type": "prometheus",
                  "uid": "${datasource}"
                },
                "exemplar": true,
                "expr": "sum(rate(container_cpu_usage_seconds_total{node=~\"$node\", namespace=~\"$namespace\", pod=~\"$pod\", container=~\"$container\"}[5m])) by (container)\n\n",
                "interval": "",
                "legendFormat": "",
                "refId": "A"
              }
            ],
            "title": "cpu usage by container",
            "type": "timeseries"
          },
          {
            "datasource": {
              "type": "prometheus",
              "uid": "${datasource}"
            },
            "fieldConfig": {
              "defaults": {
                "color": {
                  "mode": "palette-classic"
                },
                "custom": {
                  "axisLabel": "",
                  "axisPlacement": "auto",
                  "barAlignment": 0,
                  "drawStyle": "line",
                  "fillOpacity": 100,
                  "gradientMode": "none",
                  "hideFrom": {
                    "legend": false,
                    "tooltip": false,
                    "viz": false
                  },
                  "lineInterpolation": "smooth",
                  "lineWidth": 1,
                  "pointSize": 5,
                  "scaleDistribution": {
                    "type": "linear"
                  },
                  "showPoints": "never",
                  "spanNulls": false,
                  "stacking": {
                    "group": "A",
                    "mode": "none"
                  },
                  "thresholdsStyle": {
                    "mode": "off"
                  }
                },
                "mappings": [],
                "thresholds": {
                  "mode": "absolute",
                  "steps": [
                    {
                      "color": "green",
                      "value": null
                    },
                    {
                      "color": "red",
                      "value": 80
                    }
                  ]
                },
                "unit": "bytes"
              },
              "overrides": []
            },
            "gridPos": {
              "h": 8,
              "w": 12,
              "x": 12,
              "y": 4
            },
            "id": 24,
            "options": {
              "legend": {
                "calcs": [],
                "displayMode": "list",
                "placement": "bottom"
              },
              "tooltip": {
                "mode": "single"
              }
            },
            "pluginVersion": "8.3.3",
            "targets": [
              {
                "datasource": {
                  "type": "prometheus",
                  "uid": "${datasource}"
                },
                "exemplar": true,
                "expr": "sum(container_memory_usage_bytes{node=~\"$node\", namespace=~\"$namespace\", pod=~\"$pod\", container=~\"$container\"}) by (container)",
                "interval": "",
                "legendFormat": "",
                "refId": "A"
              }
            ],
            "title": "usage byets by contianer",
            "type": "timeseries"
          }
        ],
        "title": "container",
        "type": "row"
      }
    ],
    "schemaVersion": 34,
    "style": "dark",
    "tags": [],
    "templating": {
      "list": [
        {
          "current": {
            "selected": false,
            "text": "prometheus",
            "value": "prometheus"
          },
          "hide": 0,
          "includeAll": false,
          "label": "data source",
          "multi": false,
          "name": "datasource",
          "options": [],
          "query": "prometheus",
          "queryValue": "",
          "refresh": 1,
          "regex": "",
          "skipUrlSync": false,
          "type": "datasource"
        },
        {
          "current": {
            "isNone": true,
            "selected": false,
            "text": "None",
            "value": ""
          },
          "datasource": {
            "type": "prometheus",
            "uid": "${datasource}"
          },
          "definition": "label_values(up{job=\"kube-state-metrics\"}, cluster)",
          "hide": 2,
          "includeAll": false,
          "multi": false,
          "name": "cluster",
          "options": [],
          "query": {
            "query": "label_values(up{job=\"kube-state-metrics\"}, cluster)",
            "refId": "StandardVariableQuery"
          },
          "refresh": 2,
          "regex": "",
          "skipUrlSync": false,
          "sort": 1,
          "type": "query"
        },
        {
          "current": {
            "selected": true,
            "text": "monitoring-worker",
            "value": "monitoring-worker"
          },
          "datasource": {
            "type": "prometheus",
            "uid": "${datasource}"
          },
          "definition": "label_values(kube_node_info, node)",
          "hide": 0,
          "includeAll": false,
          "multi": false,
          "name": "node",
          "options": [],
          "query": {
            "query": "label_values(kube_node_info, node)",
            "refId": "StandardVariableQuery"
          },
          "refresh": 1,
          "regex": "",
          "skipUrlSync": false,
          "sort": 0,
          "type": "query"
        },
        {
          "current": {
            "selected": true,
            "text": "monitoring",
            "value": "monitoring"
          },
          "datasource": {
            "type": "prometheus",
            "uid": "${datasource}"
          },
          "definition": "label_values(kube_namespace_status_phase{job=\"kube-state-metrics\", cluster=\"$cluster\"}, namespace)",
          "hide": 0,
          "includeAll": false,
          "multi": false,
          "name": "namespace",
          "options": [],
          "query": {
            "query": "label_values(kube_namespace_status_phase{job=\"kube-state-metrics\", cluster=\"$cluster\"}, namespace)",
            "refId": "StandardVariableQuery"
          },
          "refresh": 2,
          "regex": "",
          "skipUrlSync": false,
          "sort": 1,
          "type": "query"
        },
        {
          "current": {
            "selected": false,
            "text": "alertmanager-main-0",
            "value": "alertmanager-main-0"
          },
          "datasource": {
            "type": "prometheus",
            "uid": "${datasource}"
          },
          "definition": "label_values(kube_pod_info{job=\"kube-state-metrics\", cluster=\"$cluster\", namespace=\"$namespace\"}, pod)",
          "hide": 0,
          "includeAll": false,
          "multi": false,
          "name": "pod",
          "options": [],
          "query": {
            "query": "label_values(kube_pod_info{job=\"kube-state-metrics\", cluster=\"$cluster\", namespace=\"$namespace\"}, pod)",
            "refId": "StandardVariableQuery"
          },
          "refresh": 2,
          "regex": "",
          "skipUrlSync": false,
          "sort": 1,
          "type": "query"
        },
        {
          "current": {
            "selected": false,
            "text": "alertmanager",
            "value": "alertmanager"
          },
          "datasource": {
            "type": "prometheus",
            "uid": "${datasource}"
          },
          "definition": "label_values(kube_pod_container_info{job=\"kube-state-metrics\", cluster=\"$cluster\", namespace=\"$namespace\", pod=\"$pod\"}, container)",
          "hide": 0,
          "includeAll": false,
          "multi": false,
          "name": "container",
          "options": [],
          "query": {
            "query": "label_values(kube_pod_container_info{job=\"kube-state-metrics\", cluster=\"$cluster\", namespace=\"$namespace\", pod=\"$pod\"}, container)",
            "refId": "StandardVariableQuery"
          },
          "refresh": 1,
          "regex": "",
          "skipUrlSync": false,
          "sort": 0,
          "type": "query"
        }
      ]
    },
    "time": {
      "from": "now-5m",
      "to": "now"
    },
    "timepicker": {},
    "timezone": "",
    "title": "my_dash Copy",
    "uid": "y0uv8AHIk",
    "version": 4,
    "weekStart": ""
  }
